.gitignore
AUTHORS
LICENSE
README.rst
dev_requirements.txt
setup.py
docs/Makefile
docs/source/api.rst
docs/source/conf.py
docs/source/index.rst
docs/source/message-sequence.rst
docs/source/_static/SimulationStep.png
docs/source/_static/SimulationStep.txt
src/matrixabm/__init__.py
src/matrixabm/agent.py
src/matrixabm/coordinator.py
src/matrixabm/datatypes.py
src/matrixabm/load_balancer.py
src/matrixabm/resource_manager.py
src/matrixabm/runner.py
src/matrixabm/simulator.py
src/matrixabm/state_store.py
src/matrixabm/timestep_generator.py
src/matrixabm.egg-info/PKG-INFO
src/matrixabm.egg-info/SOURCES.txt
src/matrixabm.egg-info/dependency_links.txt
src/matrixabm.egg-info/requires.txt
src/matrixabm.egg-info/top_level.txt
tests/bluepillsim.py