Metadata-Version: 2.1
Name: matrixabm
Version: 0.3.1
Summary: The Matrix ABM: An Agent Based Modeling Framework
Home-page: http://github.com/nssac/matrixabm
Author: Parantapa Bhattacharya
Author-email: pb+pypi@parantapa.net
License: UNKNOWN
Platform: UNKNOWN
Classifier: Intended Audience :: Developers
Classifier: Intended Audience :: Science/Research
Classifier: License :: OSI Approved :: MIT License
Classifier: Operating System :: POSIX :: Linux
Classifier: Programming Language :: C
Classifier: Programming Language :: Python :: 3.7
Classifier: Programming Language :: Python :: 3.8
Classifier: Topic :: Scientific/Engineering
Classifier: Topic :: System :: Distributed Computing
